alibabacloud_ess20220222/__init__.py
alibabacloud_ess20220222/client.py
alibabacloud_ess20220222/models/__init__.py
alibabacloud_ess20220222/models/_apply_eci_scaling_configuration_request.py
alibabacloud_ess20220222/models/_apply_eci_scaling_configuration_response.py
alibabacloud_ess20220222/models/_apply_eci_scaling_configuration_response_body.py
alibabacloud_ess20220222/models/_apply_scaling_group_request.py
alibabacloud_ess20220222/models/_apply_scaling_group_response.py
alibabacloud_ess20220222/models/_apply_scaling_group_response_body.py
alibabacloud_ess20220222/models/_attach_alb_server_groups_request.py
alibabacloud_ess20220222/models/_attach_alb_server_groups_response.py
alibabacloud_ess20220222/models/_attach_alb_server_groups_response_body.py
alibabacloud_ess20220222/models/_attach_dbinstances_request.py
alibabacloud_ess20220222/models/_attach_dbinstances_response.py
alibabacloud_ess20220222/models/_attach_dbinstances_response_body.py
alibabacloud_ess20220222/models/_attach_instances_request.py
alibabacloud_ess20220222/models/_attach_instances_response.py
alibabacloud_ess20220222/models/_attach_instances_response_body.py
alibabacloud_ess20220222/models/_attach_load_balancers_request.py
alibabacloud_ess20220222/models/_attach_load_balancers_response.py
alibabacloud_ess20220222/models/_attach_load_balancers_response_body.py
alibabacloud_ess20220222/models/_attach_server_groups_request.py
alibabacloud_ess20220222/models/_attach_server_groups_response.py
alibabacloud_ess20220222/models/_attach_server_groups_response_body.py
alibabacloud_ess20220222/models/_attach_vserver_groups_request.py
alibabacloud_ess20220222/models/_attach_vserver_groups_response.py
alibabacloud_ess20220222/models/_attach_vserver_groups_response_body.py
alibabacloud_ess20220222/models/_cancel_instance_refresh_request.py
alibabacloud_ess20220222/models/_cancel_instance_refresh_response.py
alibabacloud_ess20220222/models/_cancel_instance_refresh_response_body.py
alibabacloud_ess20220222-1.12.2.dist-info/LICENSE
alibabacloud_ess20220222-1.12.2.dist-info/METADATA
alibabacloud_ess20220222-1.12.2.dist-info/WHEEL
alibabacloud_ess20220222-1.12.2.dist-info/top_level.txt
alibabacloud_ess20220222-1.12.2.dist-info/RECORD
